pybalancer/__init__.py
pybalancer/pybalancer.py
pybalancer-1.0.dist-info/LICENSE
pybalancer-1.0.dist-info/METADATA
pybalancer-1.0.dist-info/WHEEL
pybalancer-1.0.dist-info/top_level.txt
pybalancer-1.0.dist-info/RECORD
