Metadata-Version: 2.1
Name: pybalancer
Version: 1.0
Summary: an simple load balancer for Python
Home-page: https://github.com/wenqf11/pybalancer
Author: Qingfu Wen
Author-email: qingfu.wen@gmail.com
License: UNKNOWN
Platform: UNKNOWN
Classifier: Programming Language :: Python :: 3
Classifier: License :: OSI Approved :: MIT License
Classifier: Operating System :: OS Independent
Requires-Dist: uhashring (>=2.1)
